{
  "Name": "DataForNerds Windows Update History",
  "Url": "https://api.datafornerds.io/v2/microsoft/windows-update-history.json",
  "GeneratedUtc": "2026-07-22T13:49:48Z",
  "TotalApiRecords": 1615,
  "ValidNormalizedRecords": 1615,
  "ClientRecordCount": 1460,
  "LatestQualityRecordCount": 21,
  "PreviewRecordCount": 263,
  "NewestReleaseDate": "2026-06-23",
  "NewestKB": "KB5095093",
  "NewestFullVersion": "10.0.26100.8737",
  "ApiProvider": "DataForNerds",
  "ApiVersion": "v2",
  "ApiDataset": "windows-update-history",
  "ApiLastModified": "07/13/2026 09:22:45",
  "ApiLastCollected": "07/14/2026 08:00:29",
  "Description": "Public Windows update reference data used for Power BI reporting."
}
